compmec/rbdyn/__classes__.py
compmec/rbdyn/__init__.py
compmec/rbdyn/__validation__.py
compmec/rbdyn/composition.py
compmec/rbdyn/energy.py
compmec/rbdyn/frames.py
compmec/rbdyn/kinematic.py
compmec/rbdyn/object.py
compmec/rbdyn/variable.py
compmec_rbdyn-0.1.0.dist-info/LICENSE.md
compmec_rbdyn-0.1.0.dist-info/METADATA
compmec_rbdyn-0.1.0.dist-info/WHEEL
compmec_rbdyn-0.1.0.dist-info/top_level.txt
compmec_rbdyn-0.1.0.dist-info/RECORD
