Metadata-Version: 2.1
Name: compmec-rbdyn
Version: 0.1.0
Summary: Rigid Body Dynamics library
Home-page: https://github.com/compmec/rbdyn
Author: Carlos Leite
Author-email: compmecgit@gmail.com
License: GPL3.0
Platform: unix
Platform: linux
Platform: osx
Platform: win32
Classifier: Programming Language :: Python :: 3
Classifier: Programming Language :: Python :: 3 :: Only
Classifier: Programming Language :: Python :: 3.6
Classifier: Programming Language :: Python :: 3.7
Classifier: Programming Language :: Python :: 3.8
Classifier: Programming Language :: Python :: 3.9
Requires-Python: >=3.6
Requires-Dist: numpy (>=1)
Requires-Dist: sympy (>=1.8)
Provides-Extra: testing
Requires-Dist: pytest (>=6.0) ; extra == 'testing'
Requires-Dist: pytest-dependency (>=0.5) ; extra == 'testing'
Requires-Dist: tox (>=3.24) ; extra == 'testing'
